{
  "updatedAt": "2026-07-11T05:11:01+00:00",
  "book": {
    "title": "Genghis Khan and the Making of the Modern World",
    "author": "Jack Weatherford"
  },
  "spotify": {
    "topTimeRange": "short_term",
    "recentTracks": [
      {
        "name": "poster boy",
        "artistNames": [
          "2hollis"
        ],
        "albumName": "2",
        "playedAt": "2026-07-10T17:26:25.185Z",
        "url": "https://open.spotify.com/track/0Gz4Q1Bmyef5yA0G6LIIQZ",
        "albumImageUrl": "https://i.scdn.co/image/ab67616d0000b273057d046c6dfb348e0215567c"
      },
      {
        "name": "Hotline Bling",
        "artistNames": [
          "Drake"
        ],
        "albumName": "Views",
        "playedAt": "2026-07-10T17:21:49.288Z",
        "url": "https://open.spotify.com/track/0wwPcA6wtMf6HUMpIRdeP7",
        "albumImageUrl": "https://i.scdn.co/image/ab67616d0000b2739416ed64daf84936d89e671c"
      },
      {
        "name": "On Sight",
        "artistNames": [
          "Kanye West"
        ],
        "albumName": "Yeezus",
        "playedAt": "2026-07-10T16:13:14.452Z",
        "url": "https://open.spotify.com/track/1gqkRc9WtOpnGIqxf2Hvzr",
        "albumImageUrl": "https://i.scdn.co/image/ab67616d0000b2731dacfbc31cc873d132958af9"
      },
      {
        "name": "Low Life (feat. The Weeknd)",
        "artistNames": [
          "Future",
          "The Weeknd"
        ],
        "albumName": "EVOL",
        "playedAt": "2026-07-10T16:05:16.118Z",
        "url": "https://open.spotify.com/track/7EiZI6JVHllARrX9PUvAdX",
        "albumImageUrl": "https://i.scdn.co/image/ab67616d0000b2732f62a05cc754995b544ec1f6"
      },
      {
        "name": "Where Have You Been",
        "artistNames": [
          "Rihanna"
        ],
        "albumName": "Talk That Talk",
        "playedAt": "2026-07-10T02:59:36.765Z",
        "url": "https://open.spotify.com/track/5WQQIDU3HRaMyPkob8mpFb",
        "albumImageUrl": "https://i.scdn.co/image/ab67616d0000b273bef074de9ca825bddaeb9f46"
      }
    ],
    "topTracks": [
      {
        "name": "90210 (feat. Kacy Hill)",
        "artistNames": [
          "Travis Scott",
          "Kacy Hill"
        ],
        "url": "https://open.spotify.com/track/51EC3I1nQXpec4gDk0mQyP"
      },
      {
        "name": "Can't Tell Me Nothing",
        "artistNames": [
          "Kanye West"
        ],
        "url": "https://open.spotify.com/track/0mEdbdeRFQwBhN4xfyIeUM"
      },
      {
        "name": "Headlines",
        "artistNames": [
          "Drake"
        ],
        "url": "https://open.spotify.com/track/6LxSe8YmdPxy095Ux6znaQ"
      },
      {
        "name": "DNA.",
        "artistNames": [
          "Kendrick Lamar"
        ],
        "url": "https://open.spotify.com/track/6HZILIRieu8S0iqY8kIKhj"
      },
      {
        "name": "DJ Got Us Fallin' In Love (feat. Pitbull)",
        "artistNames": [
          "USHER",
          "Pitbull"
        ],
        "url": "https://open.spotify.com/track/4356Typ82hUiFAynbLYbPn"
      }
    ],
    "topArtists": [
      {
        "name": "Kanye West",
        "genres": [],
        "url": "https://open.spotify.com/artist/5K4W6rqBFWDnAN6FQUkS6x"
      },
      {
        "name": "The Weeknd",
        "genres": [],
        "url": "https://open.spotify.com/artist/1Xyo4u8uXC1ZmMpatF05PJ"
      },
      {
        "name": "Michael Jackson",
        "genres": [],
        "url": "https://open.spotify.com/artist/3fMbdgg4jU18AjLCKBhRSm"
      },
      {
        "name": "Drake",
        "genres": [],
        "url": "https://open.spotify.com/artist/3TVXtAsR1Inumwj472S9r4"
      },
      {
        "name": "Don Toliver",
        "genres": [],
        "url": "https://open.spotify.com/artist/4Gso3d4CscCijv0lmajZWs"
      }
    ]
  }
}
